{"gameId":"c01ba4e1-6e4b-4acd-b547-43223ee48fff","timestamp":"2020-09-25T14:44:23.149539Z","hash":"736b238b-21cb-17e6-6db4-f7f2231e93a0","data":{"id":"c01ba4e1-6e4b-4acd-b547-43223ee48fff","day":72,"phase":4,"rules":"4ae9d46a-5408-460a-84fb-cbd8d03fff6c","shame":false,"inning":8,"season":0,"weather":1,"awayOdds":0.5642486563288637,"awayTeam":"9debc64f-74b7-4ae1-a4d6-fce0144b6ea5","homeOdds":0.4357513436711363,"homeTeam":"57ec08cc-0411-4643-b304-0e80dbc15ac7","outcomes":[],"awayBases":4,"awayScore":5,"finalized":true,"gameStart":true,"homeBases":4,"homeScore":1,"statsheet":"8870bcc4-4f7f-40ee-966c-bcd213ba7282","atBatBalls":0,"awayBatter":null,"homeBatter":null,"lastUpdate":"Game over.","awayPitcher":"3a8c52d7-4124-4a65-a20d-d51abcbe6540","awayStrikes":3,"baseRunners":[],"homePitcher":"7007cbd3-7c7b-44fd-9d6b-393e82b1c06e","homeStrikes":3,"seriesIndex":1,"terminology":"b67e9bbb-1495-4e1b-b517-f1444b0a6c8b","topOfInning":false,"atBatStrikes":0,"awayTeamName":"Houston Spies","gameComplete":true,"homeTeamName":"Mexico City Wild Wings","isPostseason":false,"seriesLength":3,"awayTeamColor":"#67556b","awayTeamEmoji":"0x1F575","basesOccupied":[],"homeTeamColor":"#d15700","homeTeamEmoji":"0x1F357","awayBatterName":null,"halfInningOuts":0,"homeBatterName":null,"awayPitcherName":"Theodore Holloway","baseRunnerNames":[],"baserunnerCount":0,"halfInningScore":0,"homePitcherName":"Rafael Davids","awayTeamNickname":"Spies","homeTeamNickname":"Wild Wings","awayTeamBatterCount":33,"homeTeamBatterCount":31}}
