{"gameId":"838e1b99-9eb7-41a8-a1ba-91d19ac6dd55","timestamp":"2020-09-25T14:44:20.824139Z","hash":"32bda093-154e-06c5-33c9-7e17a2b9845e","data":{"id":"838e1b99-9eb7-41a8-a1ba-91d19ac6dd55","day":67,"phase":4,"rules":"4ae9d46a-5408-460a-84fb-cbd8d03fff6c","shame":false,"inning":8,"season":0,"weather":1,"awayOdds":0.5772029037746932,"awayTeam":"979aee4a-6d80-4863-bf1c-ee1a78e06024","homeOdds":0.42279709622530676,"homeTeam":"bfd38797-8404-4b38-8b82-341da28b1f83","outcomes":[],"awayBases":4,"awayScore":4,"finalized":true,"gameStart":true,"homeBases":4,"homeScore":6,"statsheet":"95c55088-8866-4287-9c30-febb7b5bb218","atBatBalls":0,"awayBatter":null,"homeBatter":null,"lastUpdate":"Game over.","awayPitcher":"167751d5-210c-4a6e-9568-e92d61bab185","awayStrikes":3,"baseRunners":[],"homePitcher":"36786f44-9066-4028-98d9-4fa84465ab9e","homeStrikes":3,"seriesIndex":2,"terminology":"b67e9bbb-1495-4e1b-b517-f1444b0a6c8b","topOfInning":true,"atBatStrikes":0,"awayTeamName":"Hawaii Fridays","gameComplete":true,"homeTeamName":"Charleston Shoe Thieves","isPostseason":false,"seriesLength":3,"awayTeamColor":"#3ee652","awayTeamEmoji":"0x1F3DD","basesOccupied":[],"homeTeamColor":"#ffce0a","homeTeamEmoji":"0x1F45F","awayBatterName":null,"halfInningOuts":0,"homeBatterName":null,"awayPitcherName":"Jacob Winner","baseRunnerNames":[],"baserunnerCount":0,"halfInningScore":0,"homePitcherName":"Beasley Gloom","awayTeamNickname":"Fridays","homeTeamNickname":"Shoe Thieves","awayTeamBatterCount":32,"homeTeamBatterCount":28}}
