{"gameId":"d06608db-8bb4-47ee-9224-a6298ee6d6e6","timestamp":"2020-09-25T14:45:06.287968Z","hash":"135f77e2-8ecc-7d18-ba10-d38eca3e0b35","data":{"id":"d06608db-8bb4-47ee-9224-a6298ee6d6e6","day":21,"phase":4,"rules":"4ae9d46a-5408-460a-84fb-cbd8d03fff6c","shame":false,"inning":8,"season":1,"weather":7,"awayOdds":0.3779933064560651,"awayTeam":"b63be8c2-576a-4d6e-8daf-814f8bcea96f","homeOdds":0.6220066935439349,"homeTeam":"eb67ae5e-c4bf-46ca-bbbc-425cd34182ff","outcomes":["Rogue Umpire incinerated Dal\u00E9 hitter Jenna Maldonado! Replaced by Randy Dennis"],"awayBases":4,"awayScore":1,"finalized":true,"gameStart":true,"homeBases":4,"homeScore":5,"statsheet":"ac2d3dd3-d88d-4b6c-81f1-5cb69d883e03","atBatBalls":0,"awayBatter":null,"homeBatter":null,"lastUpdate":"Game over.","awayPitcher":"9820f2c5-f9da-4a07-b610-c2dd7bee2ef6","awayStrikes":3,"baseRunners":[],"homePitcher":"e6502bc7-5b76-4939-9fb8-132057390b30","homeStrikes":3,"seriesIndex":1,"terminology":"b67e9bbb-1495-4e1b-b517-f1444b0a6c8b","topOfInning":true,"atBatStrikes":0,"awayTeamName":"Miami Dal\u00E9","gameComplete":true,"homeTeamName":"Canada Moist Talkers","isPostseason":false,"seriesLength":3,"awayTeamColor":"#9141ba","awayTeamEmoji":"0x1F6A4","basesOccupied":[],"homeTeamColor":"#f5feff","homeTeamEmoji":"0x1F5E3","awayBatterName":null,"halfInningOuts":0,"homeBatterName":null,"awayPitcherName":"Dan Bong","baseRunnerNames":[],"baserunnerCount":0,"halfInningScore":0,"homePitcherName":"Greer Lott","awayTeamNickname":"Dal\u00E9","homeTeamNickname":"Moist Talkers","awayTeamBatterCount":36,"homeTeamBatterCount":33}}
