{"gameId":"e665cfdd-a6ea-4305-bb5c-bc8894afeed3","timestamp":"2020-09-25T14:45:01.240979Z","hash":"40e1fceb-357d-e64a-f595-9b83ecb499b3","data":{"id":"e665cfdd-a6ea-4305-bb5c-bc8894afeed3","day":11,"phase":4,"rules":"4ae9d46a-5408-460a-84fb-cbd8d03fff6c","shame":true,"inning":8,"season":1,"weather":7,"awayOdds":0.5290862147900023,"awayTeam":"eb67ae5e-c4bf-46ca-bbbc-425cd34182ff","homeOdds":0.4709137852099977,"homeTeam":"747b8e4a-7e50-4638-a973-ea7950a3e739","outcomes":[],"awayBases":4,"awayScore":4,"finalized":true,"gameStart":true,"homeBases":4,"homeScore":6,"statsheet":"f14733a8-a47b-4b67-a293-4bb3c87e73e1","atBatBalls":0,"awayBatter":null,"homeBatter":null,"lastUpdate":"Game over.","awayPitcher":"e6502bc7-5b76-4939-9fb8-132057390b30","awayStrikes":3,"baseRunners":[],"homePitcher":"afc90398-b891-4cdf-9dea-af8a3a79d793","homeStrikes":3,"seriesIndex":3,"terminology":"b67e9bbb-1495-4e1b-b517-f1444b0a6c8b","topOfInning":false,"atBatStrikes":0,"awayTeamName":"Canada Moist Talkers","gameComplete":true,"homeTeamName":"Hades Tigers","isPostseason":false,"seriesLength":3,"awayTeamColor":"#f5feff","awayTeamEmoji":"0x1F5E3","basesOccupied":[],"homeTeamColor":"#5c1c1c","homeTeamEmoji":"0x1F405","awayBatterName":null,"halfInningOuts":0,"homeBatterName":null,"awayPitcherName":"Greer Lott","baseRunnerNames":[],"baserunnerCount":0,"halfInningScore":0,"homePitcherName":"Yazmin Mason","awayTeamNickname":"Moist Talkers","homeTeamNickname":"Tigers","awayTeamBatterCount":40,"homeTeamBatterCount":35}}
