{"gameId":"a9133fd9-43f8-4152-b0a6-7765de4d3931","timestamp":"2020-09-25T14:44:35.580339Z","hash":"21c46d47-764a-0f58-0670-3195eade142c","data":{"id":"a9133fd9-43f8-4152-b0a6-7765de4d3931","day":95,"phase":4,"rules":"4ae9d46a-5408-460a-84fb-cbd8d03fff6c","shame":false,"inning":8,"season":0,"weather":1,"awayOdds":0.3743695514569363,"awayTeam":"878c1bf6-0d21-4659-bfee-916c8314d69c","homeOdds":0.6256304485430637,"homeTeam":"b024e975-1c4a-4575-8936-a3754a08806a","outcomes":[],"awayBases":4,"awayScore":2,"finalized":true,"gameStart":true,"homeBases":4,"homeScore":11,"statsheet":"2bdc450a-cbc3-4cb5-87d0-d69d4b133421","atBatBalls":0,"awayBatter":null,"homeBatter":null,"lastUpdate":"Game over.","awayPitcher":"773712f6-d76d-4caa-8a9b-56fe1d1a5a68","awayStrikes":3,"baseRunners":[],"homePitcher":"b7ca8f3f-2fdc-477b-84f4-157f2802e9b5","homeStrikes":3,"seriesIndex":3,"terminology":"b67e9bbb-1495-4e1b-b517-f1444b0a6c8b","topOfInning":true,"atBatStrikes":0,"awayTeamName":"Los Angeles Tacos","gameComplete":true,"homeTeamName":"Dallas Steaks","isPostseason":false,"seriesLength":3,"awayTeamColor":"#64376e","awayTeamEmoji":"0x1F32E","basesOccupied":[],"homeTeamColor":"#8c8d8f","homeTeamEmoji":"0x1F969","awayBatterName":null,"halfInningOuts":0,"homeBatterName":null,"awayPitcherName":"Natha Kath","baseRunnerNames":[],"baserunnerCount":0,"halfInningScore":0,"homePitcherName":"Leach Herman","awayTeamNickname":"Tacos","homeTeamNickname":"Steaks","awayTeamBatterCount":31,"homeTeamBatterCount":38}}
