{"gameId":"1d2c0014-fbe2-40e6-8f5c-7d657da6addb","timestamp":"2020-09-25T14:44:04.736435Z","hash":"01d09466-4967-540d-3fb7-c57fdb84a036","data":{"id":"1d2c0014-fbe2-40e6-8f5c-7d657da6addb","day":32,"phase":4,"rules":"4ae9d46a-5408-460a-84fb-cbd8d03fff6c","shame":false,"inning":8,"season":0,"weather":1,"awayOdds":0.47154154773750007,"awayTeam":"eb67ae5e-c4bf-46ca-bbbc-425cd34182ff","homeOdds":0.5284584522624999,"homeTeam":"9debc64f-74b7-4ae1-a4d6-fce0144b6ea5","outcomes":[],"awayBases":4,"awayScore":8,"finalized":true,"gameStart":true,"homeBases":4,"homeScore":3,"statsheet":"d655b206-9c31-47ce-83bb-3b1ce22c7524","atBatBalls":0,"awayBatter":null,"homeBatter":null,"lastUpdate":"Game over.","awayPitcher":"a691f2ba-9b69-41f8-892c-1acd42c336e4","awayStrikes":3,"baseRunners":[],"homePitcher":"3a8c52d7-4124-4a65-a20d-d51abcbe6540","homeStrikes":3,"seriesIndex":3,"terminology":"b67e9bbb-1495-4e1b-b517-f1444b0a6c8b","topOfInning":false,"atBatStrikes":0,"awayTeamName":"Canada Moist Talkers","gameComplete":true,"homeTeamName":"Houston Spies","isPostseason":false,"seriesLength":3,"awayTeamColor":"#f5feff","awayTeamEmoji":"0x1F5E3","basesOccupied":[],"homeTeamColor":"#67556b","homeTeamEmoji":"0x1F575","awayBatterName":null,"halfInningOuts":0,"homeBatterName":null,"awayPitcherName":"Jenkins Good","baseRunnerNames":[],"baserunnerCount":0,"halfInningScore":0,"homePitcherName":"Theodore Holloway","awayTeamNickname":"Moist Talkers","homeTeamNickname":"Spies","awayTeamBatterCount":40,"homeTeamBatterCount":32}}
