{"gameId":"14f1b80c-459e-4a02-9f72-e46030f9af3f","timestamp":"2020-09-25T14:45:13.633416Z","hash":"f10286cd-57db-ad0d-0bc0-9d02e4b16ec8","data":{"id":"14f1b80c-459e-4a02-9f72-e46030f9af3f","day":37,"phase":4,"rules":"4ae9d46a-5408-460a-84fb-cbd8d03fff6c","shame":false,"inning":8,"season":1,"weather":7,"awayOdds":0.5492575889273453,"awayTeam":"8d87c468-699a-47a8-b40d-cfb73a5660ad","homeOdds":0.45074241107265467,"homeTeam":"b63be8c2-576a-4d6e-8daf-814f8bcea96f","outcomes":[],"awayBases":4,"awayScore":3,"finalized":true,"gameStart":true,"homeBases":4,"homeScore":5,"statsheet":"e07e4217-1128-4e43-86f0-9bf0b55cea76","atBatBalls":0,"awayBatter":null,"homeBatter":null,"lastUpdate":"Game over.","awayPitcher":"1ffb1153-909d-44c7-9df1-6ed3a9a45bbd","awayStrikes":3,"baseRunners":[],"homePitcher":"8903a74f-f322-41d2-bd75-dbf7563c4abb","homeStrikes":3,"seriesIndex":2,"terminology":"b67e9bbb-1495-4e1b-b517-f1444b0a6c8b","topOfInning":true,"atBatStrikes":0,"awayTeamName":"Baltimore Crabs","gameComplete":true,"homeTeamName":"Miami Dal\u00E9","isPostseason":false,"seriesLength":3,"awayTeamColor":"#593037","awayTeamEmoji":"0x1F980","basesOccupied":[],"homeTeamColor":"#9141ba","homeTeamEmoji":"0x1F6A4","awayBatterName":null,"halfInningOuts":0,"homeBatterName":null,"awayPitcherName":"Montgomery Bullock","baseRunnerNames":[],"baserunnerCount":0,"halfInningScore":0,"homePitcherName":"Francisca Sasquatch","awayTeamNickname":"Crabs","homeTeamNickname":"Dal\u00E9","awayTeamBatterCount":31,"homeTeamBatterCount":32}}
