{"gameId":"52d69fa2-4ecb-491b-8e54-d0b3d60b85b7","timestamp":"2020-09-25T14:44:19.009743Z","hash":"57332988-a5b2-806a-0dce-5d7452e44756","data":{"id":"52d69fa2-4ecb-491b-8e54-d0b3d60b85b7","day":63,"phase":4,"rules":"4ae9d46a-5408-460a-84fb-cbd8d03fff6c","shame":false,"inning":8,"season":0,"weather":1,"awayOdds":0.5001500304894744,"awayTeam":"9debc64f-74b7-4ae1-a4d6-fce0144b6ea5","homeOdds":0.49984996951052557,"homeTeam":"747b8e4a-7e50-4638-a973-ea7950a3e739","outcomes":[],"awayBases":4,"awayScore":1,"finalized":true,"gameStart":true,"homeBases":4,"homeScore":5,"statsheet":"4b73d08c-d438-4bfe-a414-f71d86842fb7","atBatBalls":0,"awayBatter":null,"homeBatter":null,"lastUpdate":"Game over.","awayPitcher":"30218684-7fa1-41a5-a3b3-5d9cd97dd36b","awayStrikes":3,"baseRunners":[],"homePitcher":"7aeb8e0b-f6fb-4a9e-bba2-335dada5f0a3","homeStrikes":3,"seriesIndex":1,"terminology":"b67e9bbb-1495-4e1b-b517-f1444b0a6c8b","topOfInning":true,"atBatStrikes":0,"awayTeamName":"Houston Spies","gameComplete":true,"homeTeamName":"Hades Tigers","isPostseason":false,"seriesLength":3,"awayTeamColor":"#67556b","awayTeamEmoji":"0x1F575","basesOccupied":[],"homeTeamColor":"#5c1c1c","homeTeamEmoji":"0x1F405","awayBatterName":null,"halfInningOuts":0,"homeBatterName":null,"awayPitcherName":"Jordan Hildebert","baseRunnerNames":[],"baserunnerCount":0,"halfInningScore":0,"homePitcherName":"Dunlap Figueroa","awayTeamNickname":"Spies","homeTeamNickname":"Tigers","awayTeamBatterCount":29,"homeTeamBatterCount":32}}
