{"gameId":"8386d6e9-90ee-4f96-95c2-df62c62da95e","timestamp":"2020-09-25T14:44:59.856892Z","hash":"7e775bac-5a0c-23db-9dfc-519519ce30d6","data":{"id":"8386d6e9-90ee-4f96-95c2-df62c62da95e","day":8,"phase":4,"rules":"4ae9d46a-5408-460a-84fb-cbd8d03fff6c","shame":false,"inning":8,"season":1,"weather":7,"awayOdds":0.4846580886922052,"awayTeam":"9debc64f-74b7-4ae1-a4d6-fce0144b6ea5","homeOdds":0.5153419113077948,"homeTeam":"105bc3ff-1320-4e37-8ef0-8d595cb95dd0","outcomes":[],"awayBases":4,"awayScore":5,"finalized":true,"gameStart":true,"homeBases":4,"homeScore":2,"statsheet":"563ad3cd-de3d-441f-9675-5032f13f972a","atBatBalls":0,"awayBatter":null,"homeBatter":null,"lastUpdate":"Game over.","awayPitcher":"30218684-7fa1-41a5-a3b3-5d9cd97dd36b","awayStrikes":3,"baseRunners":[],"homePitcher":"41949d4d-b151-4f46-8bf7-73119a48fac8","homeStrikes":3,"seriesIndex":3,"terminology":"b67e9bbb-1495-4e1b-b517-f1444b0a6c8b","topOfInning":false,"atBatStrikes":0,"awayTeamName":"Houston Spies","gameComplete":true,"homeTeamName":"Seattle Garages","isPostseason":false,"seriesLength":3,"awayTeamColor":"#67556b","awayTeamEmoji":"0x1F575","basesOccupied":[],"homeTeamColor":"#2b4075","homeTeamEmoji":"0x1F3B8","awayBatterName":null,"halfInningOuts":0,"homeBatterName":null,"awayPitcherName":"Jordan Hildebert","baseRunnerNames":[],"baserunnerCount":0,"halfInningScore":0,"homePitcherName":"Ron Monstera","awayTeamNickname":"Spies","homeTeamNickname":"Garages","awayTeamBatterCount":40,"homeTeamBatterCount":35}}
