{"gameId":"122e21d8-ffea-4587-87c7-337a43c96872","timestamp":"2020-09-25T14:43:54.913626Z","hash":"9d70fa9a-807a-a232-6f96-919d124419b4","data":{"id":"122e21d8-ffea-4587-87c7-337a43c96872","day":11,"phase":4,"rules":"4ae9d46a-5408-460a-84fb-cbd8d03fff6c","shame":false,"inning":8,"season":0,"weather":1,"awayOdds":0.5016530668045851,"awayTeam":"3f8bbb15-61c0-4e3f-8e4a-907a5fb1565e","homeOdds":0.49834693319541484,"homeTeam":"747b8e4a-7e50-4638-a973-ea7950a3e739","outcomes":[],"awayBases":4,"awayScore":11,"finalized":true,"gameStart":true,"homeBases":4,"homeScore":10,"statsheet":"91a99166-75ab-4274-9bd8-316caf42333c","atBatBalls":0,"awayBatter":null,"homeBatter":null,"lastUpdate":"Game over.","awayPitcher":"3e008f60-6842-42e7-b125-b88c7e5c1a95","awayStrikes":3,"baseRunners":[],"homePitcher":"b082ca6e-eb11-4eab-8d6a-30f8be522ec4","homeStrikes":3,"seriesIndex":3,"terminology":"b67e9bbb-1495-4e1b-b517-f1444b0a6c8b","topOfInning":false,"atBatStrikes":0,"awayTeamName":"Boston Flowers","gameComplete":true,"homeTeamName":"Hades Tigers","isPostseason":false,"seriesLength":3,"awayTeamColor":"#f7d1ff","awayTeamEmoji":"0x1F339","basesOccupied":[],"homeTeamColor":"#5c1c1c","homeTeamEmoji":"0x1F405","awayBatterName":null,"halfInningOuts":0,"homeBatterName":null,"awayPitcherName":"Zeboriah Wilson","baseRunnerNames":[],"baserunnerCount":0,"halfInningScore":0,"homePitcherName":"Nicholas Mora","awayTeamNickname":"Flowers","homeTeamNickname":"Tigers","awayTeamBatterCount":44,"homeTeamBatterCount":39}}
