{"gameId":"a59bb235-e55e-4860-9a4b-efda68c50a80","timestamp":"2020-09-25T14:45:08.110071Z","hash":"18d7e0b7-fa86-09b3-041d-0a8f1125f3b2","data":{"id":"a59bb235-e55e-4860-9a4b-efda68c50a80","day":25,"phase":4,"rules":"4ae9d46a-5408-460a-84fb-cbd8d03fff6c","shame":false,"inning":8,"season":1,"weather":7,"awayOdds":0.5671653787359726,"awayTeam":"ca3f1c8c-c025-4d8e-8eef-5be6accbeb16","homeOdds":0.4328346212640273,"homeTeam":"878c1bf6-0d21-4659-bfee-916c8314d69c","outcomes":[],"awayBases":4,"awayScore":2,"finalized":true,"gameStart":true,"homeBases":4,"homeScore":0,"statsheet":"70293a2c-4c1a-4ddd-b0f6-9a25cd70cec0","atBatBalls":0,"awayBatter":"68f98a04-204f-4675-92a7-8823f2277075","homeBatter":null,"lastUpdate":"Game over.","awayPitcher":"1513aab6-142c-48c6-b43e-fbda65fd64e8","awayStrikes":3,"baseRunners":[],"homePitcher":"773712f6-d76d-4caa-8a9b-56fe1d1a5a68","homeStrikes":3,"seriesIndex":2,"terminology":"b67e9bbb-1495-4e1b-b517-f1444b0a6c8b","topOfInning":false,"atBatStrikes":0,"awayTeamName":"Chicago Firefighters","gameComplete":true,"homeTeamName":"Los Angeles Tacos","isPostseason":false,"seriesLength":3,"awayTeamColor":"#8c2a3e","awayTeamEmoji":"0x1F525","basesOccupied":[],"homeTeamColor":"#64376e","homeTeamEmoji":"0x1F32E","awayBatterName":"Isaac Johnson","halfInningOuts":0,"homeBatterName":null,"awayPitcherName":"Caleb Alvarado","baseRunnerNames":[],"baserunnerCount":0,"halfInningScore":0,"homePitcherName":"Natha Kath","awayTeamNickname":"Firefighters","homeTeamNickname":"Tacos","awayTeamBatterCount":30,"homeTeamBatterCount":33}}
