{"gameId":"3f077c8b-50d0-4c3a-a9c8-9b14615afeca","timestamp":"2020-09-25T14:44:18.531647Z","hash":"30029aa4-7147-f061-8268-35818b8a6d09","data":{"id":"3f077c8b-50d0-4c3a-a9c8-9b14615afeca","day":62,"phase":4,"rules":"4ae9d46a-5408-460a-84fb-cbd8d03fff6c","shame":false,"inning":8,"season":0,"weather":1,"awayOdds":0.3854128905402117,"awayTeam":"b63be8c2-576a-4d6e-8daf-814f8bcea96f","homeOdds":0.6145871094597882,"homeTeam":"747b8e4a-7e50-4638-a973-ea7950a3e739","outcomes":[],"awayBases":4,"awayScore":0,"finalized":true,"gameStart":true,"homeBases":4,"homeScore":7,"statsheet":"4d0f4630-96be-418c-b643-3c091b590996","atBatBalls":0,"awayBatter":null,"homeBatter":"32c9bce6-6e52-40fa-9f64-3629b3d026a8","lastUpdate":"Game over.","awayPitcher":"8903a74f-f322-41d2-bd75-dbf7563c4abb","awayStrikes":3,"baseRunners":[],"homePitcher":"2720559e-9173-4042-aaa0-d3852b72ab2e","homeStrikes":3,"seriesIndex":3,"terminology":"b67e9bbb-1495-4e1b-b517-f1444b0a6c8b","topOfInning":true,"atBatStrikes":0,"awayTeamName":"Miami Dal\u00E9","gameComplete":true,"homeTeamName":"Hades Tigers","isPostseason":false,"seriesLength":3,"awayTeamColor":"#9141ba","awayTeamEmoji":"0x1F6A4","basesOccupied":[],"homeTeamColor":"#5c1c1c","homeTeamEmoji":"0x1F405","awayBatterName":null,"halfInningOuts":0,"homeBatterName":"Ren Morin","awayPitcherName":"Francisca Sasquatch","baseRunnerNames":[],"baserunnerCount":0,"halfInningScore":0,"homePitcherName":"Hiroto Wilcox","awayTeamNickname":"Dal\u00E9","homeTeamNickname":"Tigers","awayTeamBatterCount":30,"homeTeamBatterCount":33}}
