{"gameId":"57c2eb00-0b7c-4300-abb4-4ba63830f427","timestamp":"2020-09-25T14:45:34.298882Z","hash":"679e7504-4a1c-2f68-44dc-95ea1dcd9634","data":{"id":"57c2eb00-0b7c-4300-abb4-4ba63830f427","day":82,"phase":4,"rules":"4ae9d46a-5408-460a-84fb-cbd8d03fff6c","shame":false,"inning":8,"season":1,"weather":7,"awayOdds":0.5478113902345704,"awayTeam":"a37f9158-7f82-46bc-908c-c9e2dda7c33b","homeOdds":0.45218860976542974,"homeTeam":"b72f3061-f573-40d7-832a-5ad475bd7909","outcomes":[],"awayBases":4,"awayScore":6,"finalized":true,"gameStart":true,"homeBases":4,"homeScore":1,"statsheet":"3bf0ed74-cf33-4c72-98be-d17866060daf","atBatBalls":0,"awayBatter":"678170e4-0688-436d-a02d-c0467f9af8c0","homeBatter":null,"lastUpdate":"Game over.","awayPitcher":"d5b6b11d-3924-4634-bd50-76553f1f162b","awayStrikes":3,"baseRunners":[],"homePitcher":"73265ee3-bb35-40d1-b696-1f241a6f5966","homeStrikes":3,"seriesIndex":2,"terminology":"b67e9bbb-1495-4e1b-b517-f1444b0a6c8b","topOfInning":false,"atBatStrikes":0,"awayTeamName":"Breckenridge Jazz Hands","gameComplete":true,"homeTeamName":"San Francisco Lovers","isPostseason":false,"seriesLength":3,"awayTeamColor":"#6388ad","awayTeamEmoji":"0x1F450","basesOccupied":[],"homeTeamColor":"#780018","homeTeamEmoji":"0x1F48B","awayBatterName":"Baby Doyle","halfInningOuts":0,"homeBatterName":null,"awayPitcherName":"Ogden Mendoza","baseRunnerNames":[],"baserunnerCount":0,"halfInningScore":0,"homePitcherName":"Parker Meng","awayTeamNickname":"Jazz Hands","homeTeamNickname":"Lovers","awayTeamBatterCount":41,"homeTeamBatterCount":28}}
